{
  "description": "项目配置文件。",
  "packOptions": {
    "ignore": []
  },
  "setting": {
    "urlCheck": false
  },
  "compileType": "miniprogram",
  "libVersion": "",
  "appid": "wxc0a82171cd895bc5",
  "projectname": "天天商城-多商户多级分销电商系统",
  "condition": {
    "search": {
      "current": -1,
      "list": []
    },
    "conversation": {
      "current": -1,
      "list": []
    },
    "game": {
      "current": -1,
      "list": []
    },
    "miniprogram": {
      "current": -1,
      "list": []
    }
  }
}